komo_aws_dynamodb/__init__.py
komo_aws_dynamodb/kaddb.py
komo_aws_dynamodb/settings.py
komo_aws_dynamodb-0.1.0.dist-info/WHEEL
komo_aws_dynamodb-0.1.0.dist-info/METADATA
komo_aws_dynamodb-0.1.0.dist-info/RECORD
