Metadata-Version: 2.1
Name: komo-aws-dynamodb
Version: 0.1.0
Summary: 
Author: Khosi
Author-email: khosimorafo@yahoo.com
Requires-Python: >=3.8,<4.0
Classifier: Programming Language :: Python :: 3
Classifier: Programming Language :: Python :: 3.8
Classifier: Programming Language :: Python :: 3.9
Requires-Dist: boto3 (>=1.17.94,<2.0.0)
